sentinelsys/__init__.py
sentinelsys/monitor.py
sentinelsys/visualizer.py
sentinelsys-1.4.dist-info/LICENSE
sentinelsys-1.4.dist-info/METADATA
sentinelsys-1.4.dist-info/WHEEL
sentinelsys-1.4.dist-info/top_level.txt
sentinelsys-1.4.dist-info/RECORD
