Metadata-Version: 2.1
Name: sentinelsys
Version: 1.4
Summary: Simple System Resource Monitor with Real-time Visualization
Home-page: UNKNOWN
Author: Arya Wiratama
Author-email: aryawiratama2401@gmail.com
License: UNKNOWN
Platform: UNKNOWN
Requires-Python: >=3.10
License-File: LICENSE
Requires-Dist: matplotlib
Requires-Dist: psutil
